nerval/__init__.py
nerval/nerval.py
nerval-1.1.1.dist-info/LICENCE.txt
nerval-1.1.1.dist-info/METADATA
nerval-1.1.1.dist-info/WHEEL
nerval-1.1.1.dist-info/top_level.txt
nerval-1.1.1.dist-info/RECORD
