Metadata-Version: 2.1
Name: nerval
Version: 1.1.1
Summary: Entity-level confusion matrix and classification report to evaluate Named Entity Recognition (NER) models.
Home-page: https://github.com/mdadda/nerval
Author: Mariangela D'Addato
Author-email: mdadda.py@gmail.com
Project-URL: Bug Tracker, https://github.com/mdadda/nerval/issues
Classifier: Programming Language :: Python :: 3
Classifier: License :: OSI Approved :: MIT License
Classifier: Operating System :: OS Independent
Requires-Python: >=3.6
License-File: LICENCE.txt
